{
	"events": [
		{
			"character": "",
			"event_id": "dialogic_001",
			"portrait": "",
			"text": "Esta é uma linha do tempo de teste"
		},
		{
			"character": "",
			"event_id": "dialogic_001",
			"portrait": "",
			"text": "Iremos aprender aos poucos como usar esta ferramenta"
		},
		{
			"character": "",
			"event_id": "dialogic_001",
			"portrait": "",
			"text": "Ao final, faremos um pequeno protótipo dessa idéia tão bacana :)"
		},
		{
			"character": "",
			"event_id": "dialogic_010",
			"options": [

			],
			"portrait": "",
			"question": "Feshow?"
		},
		{
			"choice": "Sim",
			"condition": "",
			"definition": "",
			"event_id": "dialogic_011",
			"value": ""
		},
		{
			"character": "",
			"event_id": "dialogic_001",
			"portrait": "",
			"text": "Então bora trabaiá"
		},
		{
			"choice": "Com certeza",
			"condition": "",
			"definition": "",
			"event_id": "dialogic_011",
			"value": ""
		},
		{
			"character": "",
			"event_id": "dialogic_001",
			"portrait": "",
			"text": "Então vamos nessa, camarada!"
		},
		{
			"choice": "Não...",
			"condition": "",
			"definition": "",
			"event_id": "dialogic_011",
			"value": ""
		},
		{
			"character": "",
			"event_id": "dialogic_001",
			"portrait": "",
			"text": "..."
		},
		{
			"event_id": "dialogic_013"
		},
		{
			"change_scene": "res://Source/Menu/Menu.tscn",
			"event_id": "dialogic_041"
		}
	],
	"metadata": {
		"dialogic-version": "1.4.5",
		"file": "timeline-1671746402.json",
		"name": "Teste"
	}
}
